LICENSE
MANIFEST.in
README.md
setup.py
hse2/__init__.py
hse2/hse.c
hse2/hse.pyi
hse2/hse.pyx
hse2/limits.c
hse2/limits.pyi
hse2/limits.pyx
hse2/py.typed
hse2/version.c
hse2/version.pyi
hse2/version.pyx
hse2.egg-info/PKG-INFO
hse2.egg-info/SOURCES.txt
hse2.egg-info/dependency_links.txt
hse2.egg-info/not-zip-safe
hse2.egg-info/top_level.txt