Metadata-Version: 2.1
Name: hse2
Version: 2.0.2
Summary: HSE is a fast embeddable key-value store designed for SSDs and persistent memory.
Home-page: https://github.com/hse-project/hse-python
Maintainer: Micron HSE
Maintainer-email: hse@micron.com
License: Apache-2.0
Project-URL: repohome, https://github.com/hse-project/hse-python
Project-URL: projecthome, https://hse-project.github.io
Keywords: micron,hse,key,value,database,bindings,heterogeneous,memory,storage,engine
Platform: UNKNOWN
Classifier: License :: OSI Approved :: Apache Software License
Classifier: Operating System :: POSIX :: Linux
Classifier: Programming Language :: Cython
Classifier: Programming Language :: Python :: 3 :: Only
Classifier: Topic :: Database
Classifier: Topic :: Database :: Database Engines/Servers
Classifier: Typing :: Typed
